{"time":{"updated":"Jul 31, 2021 11:24:00 UTC","updatedISO":"2021-07-31T11:24:00+00:00","updateduk":"Jul 31, 2021 at 12:24 BST"},"disclaimer":"This data was produced from the CoinDesk Bitcoin Price Index (USD). Non-USD currency data converted using hourly conversion rate from openexchangerates.org","chartName":"Bitcoin","bpi":{"USD":{"code":"USD","symbol":"&#36;","rate":"41,528.7783","description":"United States Dollar","rate_float":41528.7783},"GBP":{"code":"GBP","symbol":"&pound;","rate":"29,866.0854","description":"British Pound Sterling","rate_float":29866.0854},"EUR":{"code":"EUR","symbol":"&euro;","rate":"34,995.1802","description":"Euro","rate_float":34995.1802},"CNY":{"code":"CNY","symbol":"&yen;","rate":"40,202.5000","description":"Chinese Yuan","rate_float":40202.5}}}