{"time":{"updated":"Feb 1, 2022 23:47:00 UTC","updatedISO":"2022-02-01T23:47:00+00:00","updateduk":"Feb 1, 2022 at 23:47 GMT"},"disclaimer":"This data was produced from the CoinDesk Bitcoin Price Index (USD). Non-USD currency data converted using hourly conversion rate from openexchangerates.org","chartName":"Bitcoin","bpi":{"USD":{"code":"USD","symbol":"&#36;","rate":"38,812.0650","description":"United States Dollar","rate_float":38812.065},"GBP":{"code":"GBP","symbol":"&pound;","rate":"28,697.9902","description":"British Pound Sterling","rate_float":28697.9902},"EUR":{"code":"EUR","symbol":"&euro;","rate":"34,434.8791","description":"Euro","rate_float":34434.8791},"CNY":{"code":"CNY","symbol":"&yen;","rate":"40,202.5000","description":"Chinese Yuan","rate_float":40202.5}}}