{"time":{"updated":"May 10, 2021 17:11:00 UTC","updatedISO":"2021-05-10T17:11:00+00:00","updateduk":"May 10, 2021 at 18:11 BST"},"disclaimer":"This data was produced from the CoinDesk Bitcoin Price Index (USD). Non-USD currency data converted using hourly conversion rate from openexchangerates.org","chartName":"Bitcoin","bpi":{"USD":{"code":"USD","symbol":"&#36;","rate":"57,733.7915","description":"United States Dollar","rate_float":57733.7915},"GBP":{"code":"GBP","symbol":"&pound;","rate":"40,823.2175","description":"British Pound Sterling","rate_float":40823.2175},"EUR":{"code":"EUR","symbol":"&euro;","rate":"47,481.6557","description":"Euro","rate_float":47481.6557},"CNY":{"code":"CNY","symbol":"&yen;","rate":"40,202.5000","description":"Chinese Yuan","rate_float":40202.5}}}