{"time":{"updated":"Oct 4, 2021 08:41:00 UTC","updatedISO":"2021-10-04T08:41:00+00:00","updateduk":"Oct 4, 2021 at 09:41 BST"},"disclaimer":"This data was produced from the CoinDesk Bitcoin Price Index (USD). Non-USD currency data converted using hourly conversion rate from openexchangerates.org","chartName":"Bitcoin","bpi":{"USD":{"code":"USD","symbol":"&#36;","rate":"47,560.9517","description":"United States Dollar","rate_float":47560.9517},"GBP":{"code":"GBP","symbol":"&pound;","rate":"35,067.8311","description":"British Pound Sterling","rate_float":35067.8311},"EUR":{"code":"EUR","symbol":"&euro;","rate":"40,968.7184","description":"Euro","rate_float":40968.7184},"CNY":{"code":"CNY","symbol":"&yen;","rate":"40,202.5000","description":"Chinese Yuan","rate_float":40202.5}}}