{"time":{"updated":"Sep 5, 2021 19:45:00 UTC","updatedISO":"2021-09-05T19:45:00+00:00","updateduk":"Sep 5, 2021 at 20:45 BST"},"disclaimer":"This data was produced from the CoinDesk Bitcoin Price Index (USD). Non-USD currency data converted using hourly conversion rate from openexchangerates.org","chartName":"Bitcoin","bpi":{"USD":{"code":"USD","symbol":"&#36;","rate":"50,738.1283","description":"United States Dollar","rate_float":50738.1283},"GBP":{"code":"GBP","symbol":"&pound;","rate":"36,594.4184","description":"British Pound Sterling","rate_float":36594.4184},"EUR":{"code":"EUR","symbol":"&euro;","rate":"42,696.2872","description":"Euro","rate_float":42696.2872},"CNY":{"code":"CNY","symbol":"&yen;","rate":"40,202.5000","description":"Chinese Yuan","rate_float":40202.5}}}