{"time":{"updated":"Jun 17, 2021 13:42:00 UTC","updatedISO":"2021-06-17T13:42:00+00:00","updateduk":"Jun 17, 2021 at 14:42 BST"},"disclaimer":"This data was produced from the CoinDesk Bitcoin Price Index (USD). Non-USD currency data converted using hourly conversion rate from openexchangerates.org","chartName":"Bitcoin","bpi":{"USD":{"code":"USD","symbol":"&#36;","rate":"38,791.1931","description":"United States Dollar","rate_float":38791.1931},"GBP":{"code":"GBP","symbol":"&pound;","rate":"27,853.0852","description":"British Pound Sterling","rate_float":27853.0852},"EUR":{"code":"EUR","symbol":"&euro;","rate":"32,512.4506","description":"Euro","rate_float":32512.4506},"CNY":{"code":"CNY","symbol":"&yen;","rate":"40,202.5000","description":"Chinese Yuan","rate_float":40202.5}}}