{"time":{"updated":"May 6, 2021 11:54:00 UTC","updatedISO":"2021-05-06T11:54:00+00:00","updateduk":"May 6, 2021 at 12:54 BST"},"disclaimer":"This data was produced from the CoinDesk Bitcoin Price Index (USD). Non-USD currency data converted using hourly conversion rate from openexchangerates.org","chartName":"Bitcoin","bpi":{"USD":{"code":"USD","symbol":"&#36;","rate":"58,046.5519","description":"United States Dollar","rate_float":58046.5519},"GBP":{"code":"GBP","symbol":"&pound;","rate":"41,772.6206","description":"British Pound Sterling","rate_float":41772.6206},"EUR":{"code":"EUR","symbol":"&euro;","rate":"48,204.2947","description":"Euro","rate_float":48204.2947},"CNY":{"code":"CNY","symbol":"&yen;","rate":"40,202.5000","description":"Chinese Yuan","rate_float":40202.5}}}