{"time":{"updated":"Jun 28, 2021 10:13:00 UTC","updatedISO":"2021-06-28T10:13:00+00:00","updateduk":"Jun 28, 2021 at 11:13 BST"},"disclaimer":"This data was produced from the CoinDesk Bitcoin Price Index (USD). Non-USD currency data converted using hourly conversion rate from openexchangerates.org","chartName":"Bitcoin","bpi":{"USD":{"code":"USD","symbol":"&#36;","rate":"34,260.9683","description":"United States Dollar","rate_float":34260.9683},"GBP":{"code":"GBP","symbol":"&pound;","rate":"24,620.9597","description":"British Pound Sterling","rate_float":24620.9597},"EUR":{"code":"EUR","symbol":"&euro;","rate":"28,702.2975","description":"Euro","rate_float":28702.2975},"CNY":{"code":"CNY","symbol":"&yen;","rate":"40,202.5000","description":"Chinese Yuan","rate_float":40202.5}}}