{"time":{"updated":"Jul 2, 2021 17:40:00 UTC","updatedISO":"2021-07-02T17:40:00+00:00","updateduk":"Jul 2, 2021 at 18:40 BST"},"disclaimer":"This data was produced from the CoinDesk Bitcoin Price Index (USD). Non-USD currency data converted using hourly conversion rate from openexchangerates.org","chartName":"Bitcoin","bpi":{"USD":{"code":"USD","symbol":"&#36;","rate":"33,548.9150","description":"United States Dollar","rate_float":33548.915},"GBP":{"code":"GBP","symbol":"&pound;","rate":"24,303.6392","description":"British Pound Sterling","rate_float":24303.6392},"EUR":{"code":"EUR","symbol":"&euro;","rate":"28,327.4625","description":"Euro","rate_float":28327.4625},"CNY":{"code":"CNY","symbol":"&yen;","rate":"40,202.5000","description":"Chinese Yuan","rate_float":40202.5}}}