{"time":{"updated":"Aug 6, 2021 02:50:00 UTC","updatedISO":"2021-08-06T02:50:00+00:00","updateduk":"Aug 6, 2021 at 03:50 BST"},"disclaimer":"This data was produced from the CoinDesk Bitcoin Price Index (USD). Non-USD currency data converted using hourly conversion rate from openexchangerates.org","chartName":"Bitcoin","bpi":{"USD":{"code":"USD","symbol":"&#36;","rate":"40,305.0033","description":"United States Dollar","rate_float":40305.0033},"GBP":{"code":"GBP","symbol":"&pound;","rate":"28,957.2103","description":"British Pound Sterling","rate_float":28957.2103},"EUR":{"code":"EUR","symbol":"&euro;","rate":"34,080.6614","description":"Euro","rate_float":34080.6614},"CNY":{"code":"CNY","symbol":"&yen;","rate":"40,202.5000","description":"Chinese Yuan","rate_float":40202.5}}}