{"time":{"updated":"Apr 28, 2021 10:38:00 UTC","updatedISO":"2021-04-28T10:38:00+00:00","updateduk":"Apr 28, 2021 at 11:38 BST"},"disclaimer":"This data was produced from the CoinDesk Bitcoin Price Index (USD). Non-USD currency data converted using hourly conversion rate from openexchangerates.org","chartName":"Bitcoin","bpi":{"USD":{"code":"USD","symbol":"&#36;","rate":"54,357.5950","description":"United States Dollar","rate_float":54357.595},"GBP":{"code":"GBP","symbol":"&pound;","rate":"39,137.0879","description":"British Pound Sterling","rate_float":39137.0879},"EUR":{"code":"EUR","symbol":"&euro;","rate":"45,049.3461","description":"Euro","rate_float":45049.3461},"CNY":{"code":"CNY","symbol":"&yen;","rate":"40,202.5000","description":"Chinese Yuan","rate_float":40202.5}}}