{"time":{"updated":"Jul 12, 2021 21:31:00 UTC","updatedISO":"2021-07-12T21:31:00+00:00","updateduk":"Jul 12, 2021 at 22:31 BST"},"disclaimer":"This data was produced from the CoinDesk Bitcoin Price Index (USD). Non-USD currency data converted using hourly conversion rate from openexchangerates.org","chartName":"Bitcoin","bpi":{"USD":{"code":"USD","symbol":"&#36;","rate":"32,828.4417","description":"United States Dollar","rate_float":32828.4417},"GBP":{"code":"GBP","symbol":"&pound;","rate":"23,646.1296","description":"British Pound Sterling","rate_float":23646.1296},"EUR":{"code":"EUR","symbol":"&euro;","rate":"27,677.8233","description":"Euro","rate_float":27677.8233},"CNY":{"code":"CNY","symbol":"&yen;","rate":"40,202.5000","description":"Chinese Yuan","rate_float":40202.5}}}