{"time":{"updated":"Jul 30, 2021 13:02:00 UTC","updatedISO":"2021-07-30T13:02:00+00:00","updateduk":"Jul 30, 2021 at 14:02 BST"},"disclaimer":"This data was produced from the CoinDesk Bitcoin Price Index (USD). Non-USD currency data converted using hourly conversion rate from openexchangerates.org","chartName":"Bitcoin","bpi":{"USD":{"code":"USD","symbol":"&#36;","rate":"38,785.1983","description":"United States Dollar","rate_float":38785.1983},"GBP":{"code":"GBP","symbol":"&pound;","rate":"27,789.8661","description":"British Pound Sterling","rate_float":27789.8661},"EUR":{"code":"EUR","symbol":"&euro;","rate":"32,636.6196","description":"Euro","rate_float":32636.6196},"CNY":{"code":"CNY","symbol":"&yen;","rate":"40,202.5000","description":"Chinese Yuan","rate_float":40202.5}}}