{"time":{"updated":"Aug 5, 2021 19:23:00 UTC","updatedISO":"2021-08-05T19:23:00+00:00","updateduk":"Aug 5, 2021 at 20:23 BST"},"disclaimer":"This data was produced from the CoinDesk Bitcoin Price Index (USD). Non-USD currency data converted using hourly conversion rate from openexchangerates.org","chartName":"Bitcoin","bpi":{"USD":{"code":"USD","symbol":"&#36;","rate":"41,233.0900","description":"United States Dollar","rate_float":41233.09},"GBP":{"code":"GBP","symbol":"&pound;","rate":"29,595.3390","description":"British Pound Sterling","rate_float":29595.339},"EUR":{"code":"EUR","symbol":"&euro;","rate":"34,837.4254","description":"Euro","rate_float":34837.4254},"CNY":{"code":"CNY","symbol":"&yen;","rate":"40,202.5000","description":"Chinese Yuan","rate_float":40202.5}}}