{"time":{"updated":"Aug 29, 2021 22:00:00 UTC","updatedISO":"2021-08-29T22:00:00+00:00","updateduk":"Aug 29, 2021 at 23:00 BST"},"disclaimer":"This data was produced from the CoinDesk Bitcoin Price Index (USD). Non-USD currency data converted using hourly conversion rate from openexchangerates.org","chartName":"Bitcoin","bpi":{"USD":{"code":"USD","symbol":"&#36;","rate":"48,951.0298","description":"United States Dollar","rate_float":48951.0298},"GBP":{"code":"GBP","symbol":"&pound;","rate":"35,572.8112","description":"British Pound Sterling","rate_float":35572.8112},"EUR":{"code":"EUR","symbol":"&euro;","rate":"41,497.0607","description":"Euro","rate_float":41497.0607},"CNY":{"code":"CNY","symbol":"&yen;","rate":"40,202.5000","description":"Chinese Yuan","rate_float":40202.5}}}