{"time":{"updated":"Jun 23, 2021 19:22:00 UTC","updatedISO":"2021-06-23T19:22:00+00:00","updateduk":"Jun 23, 2021 at 20:22 BST"},"disclaimer":"This data was produced from the CoinDesk Bitcoin Price Index (USD). Non-USD currency data converted using hourly conversion rate from openexchangerates.org","chartName":"Bitcoin","bpi":{"USD":{"code":"USD","symbol":"&#36;","rate":"33,400.2414","description":"United States Dollar","rate_float":33400.2414},"GBP":{"code":"GBP","symbol":"&pound;","rate":"23,918.5141","description":"British Pound Sterling","rate_float":23918.5141},"EUR":{"code":"EUR","symbol":"&euro;","rate":"27,998.4872","description":"Euro","rate_float":27998.4872},"CNY":{"code":"CNY","symbol":"&yen;","rate":"40,202.5000","description":"Chinese Yuan","rate_float":40202.5}}}