{"time":{"updated":"Apr 29, 2021 03:07:00 UTC","updatedISO":"2021-04-29T03:07:00+00:00","updateduk":"Apr 29, 2021 at 04:07 BST"},"disclaimer":"This data was produced from the CoinDesk Bitcoin Price Index (USD). Non-USD currency data converted using hourly conversion rate from openexchangerates.org","chartName":"Bitcoin","bpi":{"USD":{"code":"USD","symbol":"&#36;","rate":"54,618.1150","description":"United States Dollar","rate_float":54618.115},"GBP":{"code":"GBP","symbol":"&pound;","rate":"39,143.2737","description":"British Pound Sterling","rate_float":39143.2737},"EUR":{"code":"EUR","symbol":"&euro;","rate":"45,000.4111","description":"Euro","rate_float":45000.4111},"CNY":{"code":"CNY","symbol":"&yen;","rate":"40,202.5000","description":"Chinese Yuan","rate_float":40202.5}}}