{"time":{"updated":"Oct 2, 2021 06:52:00 UTC","updatedISO":"2021-10-02T06:52:00+00:00","updateduk":"Oct 2, 2021 at 07:52 BST"},"disclaimer":"This data was produced from the CoinDesk Bitcoin Price Index (USD). Non-USD currency data converted using hourly conversion rate from openexchangerates.org","chartName":"Bitcoin","bpi":{"USD":{"code":"USD","symbol":"&#36;","rate":"47,822.1550","description":"United States Dollar","rate_float":47822.155},"GBP":{"code":"GBP","symbol":"&pound;","rate":"35,306.1406","description":"British Pound Sterling","rate_float":35306.1406},"EUR":{"code":"EUR","symbol":"&euro;","rate":"41,247.5173","description":"Euro","rate_float":41247.5173},"CNY":{"code":"CNY","symbol":"&yen;","rate":"40,202.5000","description":"Chinese Yuan","rate_float":40202.5}}}