{"time":{"updated":"Jun 25, 2021 09:06:00 UTC","updatedISO":"2021-06-25T09:06:00+00:00","updateduk":"Jun 25, 2021 at 10:06 BST"},"disclaimer":"This data was produced from the CoinDesk Bitcoin Price Index (USD). Non-USD currency data converted using hourly conversion rate from openexchangerates.org","chartName":"Bitcoin","bpi":{"USD":{"code":"USD","symbol":"&#36;","rate":"34,314.2811","description":"United States Dollar","rate_float":34314.2811},"GBP":{"code":"GBP","symbol":"&pound;","rate":"24,666.6494","description":"British Pound Sterling","rate_float":24666.6494},"EUR":{"code":"EUR","symbol":"&euro;","rate":"28,730.3525","description":"Euro","rate_float":28730.3525},"CNY":{"code":"CNY","symbol":"&yen;","rate":"40,202.5000","description":"Chinese Yuan","rate_float":40202.5}}}