{"time":{"updated":"Jul 7, 2021 02:31:00 UTC","updatedISO":"2021-07-07T02:31:00+00:00","updateduk":"Jul 7, 2021 at 03:31 BST"},"disclaimer":"This data was produced from the CoinDesk Bitcoin Price Index (USD). Non-USD currency data converted using hourly conversion rate from openexchangerates.org","chartName":"Bitcoin","bpi":{"USD":{"code":"USD","symbol":"&#36;","rate":"34,090.2282","description":"United States Dollar","rate_float":34090.2282},"GBP":{"code":"GBP","symbol":"&pound;","rate":"24,693.5636","description":"British Pound Sterling","rate_float":24693.5636},"EUR":{"code":"EUR","symbol":"&euro;","rate":"28,833.6513","description":"Euro","rate_float":28833.6513},"CNY":{"code":"CNY","symbol":"&yen;","rate":"40,202.5000","description":"Chinese Yuan","rate_float":40202.5}}}