{"time":{"updated":"Jul 7, 2021 17:09:00 UTC","updatedISO":"2021-07-07T17:09:00+00:00","updateduk":"Jul 7, 2021 at 18:09 BST"},"disclaimer":"This data was produced from the CoinDesk Bitcoin Price Index (USD). Non-USD currency data converted using hourly conversion rate from openexchangerates.org","chartName":"Bitcoin","bpi":{"USD":{"code":"USD","symbol":"&#36;","rate":"34,577.5900","description":"United States Dollar","rate_float":34577.59},"GBP":{"code":"GBP","symbol":"&pound;","rate":"25,061.6643","description":"British Pound Sterling","rate_float":25061.6643},"EUR":{"code":"EUR","symbol":"&euro;","rate":"29,301.9142","description":"Euro","rate_float":29301.9142},"CNY":{"code":"CNY","symbol":"&yen;","rate":"40,202.5000","description":"Chinese Yuan","rate_float":40202.5}}}