{"time":{"updated":"Jun 12, 2021 19:51:00 UTC","updatedISO":"2021-06-12T19:51:00+00:00","updateduk":"Jun 12, 2021 at 20:51 BST"},"disclaimer":"This data was produced from the CoinDesk Bitcoin Price Index (USD). Non-USD currency data converted using hourly conversion rate from openexchangerates.org","chartName":"Bitcoin","bpi":{"USD":{"code":"USD","symbol":"&#36;","rate":"35,749.8717","description":"United States Dollar","rate_float":35749.8717},"GBP":{"code":"GBP","symbol":"&pound;","rate":"25,341.0463","description":"British Pound Sterling","rate_float":25341.0463},"EUR":{"code":"EUR","symbol":"&euro;","rate":"29,523.4953","description":"Euro","rate_float":29523.4953},"CNY":{"code":"CNY","symbol":"&yen;","rate":"40,202.5000","description":"Chinese Yuan","rate_float":40202.5}}}