{"time":{"updated":"Jul 31, 2021 22:40:00 UTC","updatedISO":"2021-07-31T22:40:00+00:00","updateduk":"Jul 31, 2021 at 23:40 BST"},"disclaimer":"This data was produced from the CoinDesk Bitcoin Price Index (USD). Non-USD currency data converted using hourly conversion rate from openexchangerates.org","chartName":"Bitcoin","bpi":{"USD":{"code":"USD","symbol":"&#36;","rate":"41,840.4467","description":"United States Dollar","rate_float":41840.4467},"GBP":{"code":"GBP","symbol":"&pound;","rate":"30,090.2267","description":"British Pound Sterling","rate_float":30090.2267},"EUR":{"code":"EUR","symbol":"&euro;","rate":"35,257.8147","description":"Euro","rate_float":35257.8147},"CNY":{"code":"CNY","symbol":"&yen;","rate":"40,202.5000","description":"Chinese Yuan","rate_float":40202.5}}}