{"time":{"updated":"Oct 4, 2021 09:47:00 UTC","updatedISO":"2021-10-04T09:47:00+00:00","updateduk":"Oct 4, 2021 at 10:47 BST"},"disclaimer":"This data was produced from the CoinDesk Bitcoin Price Index (USD). Non-USD currency data converted using hourly conversion rate from openexchangerates.org","chartName":"Bitcoin","bpi":{"USD":{"code":"USD","symbol":"&#36;","rate":"47,716.8850","description":"United States Dollar","rate_float":47716.885},"GBP":{"code":"GBP","symbol":"&pound;","rate":"35,190.1052","description":"British Pound Sterling","rate_float":35190.1052},"EUR":{"code":"EUR","symbol":"&euro;","rate":"41,090.3935","description":"Euro","rate_float":41090.3935},"CNY":{"code":"CNY","symbol":"&yen;","rate":"40,202.5000","description":"Chinese Yuan","rate_float":40202.5}}}