{"time":{"updated":"Dec 1, 2021 16:14:00 UTC","updatedISO":"2021-12-01T16:14:00+00:00","updateduk":"Dec 1, 2021 at 16:14 GMT"},"disclaimer":"This data was produced from the CoinDesk Bitcoin Price Index (USD). Non-USD currency data converted using hourly conversion rate from openexchangerates.org","chartName":"Bitcoin","bpi":{"USD":{"code":"USD","symbol":"&#36;","rate":"58,979.6817","description":"United States Dollar","rate_float":58979.6817},"GBP":{"code":"GBP","symbol":"&pound;","rate":"44,302.8238","description":"British Pound Sterling","rate_float":44302.8238},"EUR":{"code":"EUR","symbol":"&euro;","rate":"52,035.0011","description":"Euro","rate_float":52035.0011},"CNY":{"code":"CNY","symbol":"&yen;","rate":"40,202.5000","description":"Chinese Yuan","rate_float":40202.5}}}