{"time":{"updated":"Apr 26, 2021 23:10:00 UTC","updatedISO":"2021-04-26T23:10:00+00:00","updateduk":"Apr 27, 2021 at 00:10 BST"},"disclaimer":"This data was produced from the CoinDesk Bitcoin Price Index (USD). Non-USD currency data converted using hourly conversion rate from openexchangerates.org","chartName":"Bitcoin","bpi":{"USD":{"code":"USD","symbol":"&#36;","rate":"53,748.0283","description":"United States Dollar","rate_float":53748.0283},"GBP":{"code":"GBP","symbol":"&pound;","rate":"38,676.7587","description":"British Pound Sterling","rate_float":38676.7587},"EUR":{"code":"EUR","symbol":"&euro;","rate":"44,484.0719","description":"Euro","rate_float":44484.0719},"CNY":{"code":"CNY","symbol":"&yen;","rate":"40,202.5000","description":"Chinese Yuan","rate_float":40202.5}}}