{"time":{"updated":"Jul 12, 2021 04:40:00 UTC","updatedISO":"2021-07-12T04:40:00+00:00","updateduk":"Jul 12, 2021 at 05:40 BST"},"disclaimer":"This data was produced from the CoinDesk Bitcoin Price Index (USD). Non-USD currency data converted using hourly conversion rate from openexchangerates.org","chartName":"Bitcoin","bpi":{"USD":{"code":"USD","symbol":"&#36;","rate":"34,325.7475","description":"United States Dollar","rate_float":34325.7475},"GBP":{"code":"GBP","symbol":"&pound;","rate":"24,719.9616","description":"British Pound Sterling","rate_float":24719.9616},"EUR":{"code":"EUR","symbol":"&euro;","rate":"28,920.6436","description":"Euro","rate_float":28920.6436},"CNY":{"code":"CNY","symbol":"&yen;","rate":"40,202.5000","description":"Chinese Yuan","rate_float":40202.5}}}