{"time":{"updated":"Jul 28, 2021 03:02:00 UTC","updatedISO":"2021-07-28T03:02:00+00:00","updateduk":"Jul 28, 2021 at 04:02 BST"},"disclaimer":"This data was produced from the CoinDesk Bitcoin Price Index (USD). Non-USD currency data converted using hourly conversion rate from openexchangerates.org","chartName":"Bitcoin","bpi":{"USD":{"code":"USD","symbol":"&#36;","rate":"39,696.4550","description":"United States Dollar","rate_float":39696.455},"GBP":{"code":"GBP","symbol":"&pound;","rate":"28,591.6099","description":"British Pound Sterling","rate_float":28591.6099},"EUR":{"code":"EUR","symbol":"&euro;","rate":"33,577.4052","description":"Euro","rate_float":33577.4052},"CNY":{"code":"CNY","symbol":"&yen;","rate":"40,202.5000","description":"Chinese Yuan","rate_float":40202.5}}}