{"time":{"updated":"Apr 27, 2021 14:21:00 UTC","updatedISO":"2021-04-27T14:21:00+00:00","updateduk":"Apr 27, 2021 at 15:21 BST"},"disclaimer":"This data was produced from the CoinDesk Bitcoin Price Index (USD). Non-USD currency data converted using hourly conversion rate from openexchangerates.org","chartName":"Bitcoin","bpi":{"USD":{"code":"USD","symbol":"&#36;","rate":"54,615.9706","description":"United States Dollar","rate_float":54615.9706},"GBP":{"code":"GBP","symbol":"&pound;","rate":"39,287.5615","description":"British Pound Sterling","rate_float":39287.5615},"EUR":{"code":"EUR","symbol":"&euro;","rate":"45,195.3711","description":"Euro","rate_float":45195.3711},"CNY":{"code":"CNY","symbol":"&yen;","rate":"40,202.5000","description":"Chinese Yuan","rate_float":40202.5}}}