{"time":{"updated":"May 1, 2024 00:16:56 UTC","updatedISO":"2024-05-01T00:16:56+00:00","updateduk":"May 1, 2024 at 01:16 BST"},"disclaimer":"This data was produced from the CoinDesk Bitcoin Price Index (USD). Non-USD currency data converted using hourly conversion rate from openexchangerates.org","chartName":"Bitcoin","bpi":{"USD":{"code":"USD","symbol":"&#36;","rate":"60,637.634","description":"United States Dollar","rate_float":60637.6337},"GBP":{"code":"GBP","symbol":"&pound;","rate":"48,542.669","description":"British Pound Sterling","rate_float":48542.6693},"EUR":{"code":"EUR","symbol":"&euro;","rate":"56,843.052","description":"Euro","rate_float":56843.0518},"CNY":{"code":"CNY","symbol":"&yen;","rate":"439,119.552","description":"Chinese Yuan","rate_float":439119.5516}}}