{"time":{"updated":"Jul 31, 2021 23:38:00 UTC","updatedISO":"2021-07-31T23:38:00+00:00","updateduk":"Aug 1, 2021 at 00:38 BST"},"disclaimer":"This data was produced from the CoinDesk Bitcoin Price Index (USD). Non-USD currency data converted using hourly conversion rate from openexchangerates.org","chartName":"Bitcoin","bpi":{"USD":{"code":"USD","symbol":"&#36;","rate":"41,841.3467","description":"United States Dollar","rate_float":41841.3467},"GBP":{"code":"GBP","symbol":"&pound;","rate":"30,090.8739","description":"British Pound Sterling","rate_float":30090.8739},"EUR":{"code":"EUR","symbol":"&euro;","rate":"35,258.5731","description":"Euro","rate_float":35258.5731},"CNY":{"code":"CNY","symbol":"&yen;","rate":"40,202.5000","description":"Chinese Yuan","rate_float":40202.5}}}