{"time":{"updated":"Jun 10, 2021 11:54:00 UTC","updatedISO":"2021-06-10T11:54:00+00:00","updateduk":"Jun 10, 2021 at 12:54 BST"},"disclaimer":"This data was produced from the CoinDesk Bitcoin Price Index (USD). Non-USD currency data converted using hourly conversion rate from openexchangerates.org","chartName":"Bitcoin","bpi":{"USD":{"code":"USD","symbol":"&#36;","rate":"37,810.9137","description":"United States Dollar","rate_float":37810.9137},"GBP":{"code":"GBP","symbol":"&pound;","rate":"26,823.4403","description":"British Pound Sterling","rate_float":26823.4403},"EUR":{"code":"EUR","symbol":"&euro;","rate":"31,072.6307","description":"Euro","rate_float":31072.6307},"CNY":{"code":"CNY","symbol":"&yen;","rate":"40,202.5000","description":"Chinese Yuan","rate_float":40202.5}}}