{"time":{"updated":"Jun 14, 2021 23:22:00 UTC","updatedISO":"2021-06-14T23:22:00+00:00","updateduk":"Jun 15, 2021 at 00:22 BST"},"disclaimer":"This data was produced from the CoinDesk Bitcoin Price Index (USD). Non-USD currency data converted using hourly conversion rate from openexchangerates.org","chartName":"Bitcoin","bpi":{"USD":{"code":"USD","symbol":"&#36;","rate":"40,436.0600","description":"United States Dollar","rate_float":40436.06},"GBP":{"code":"GBP","symbol":"&pound;","rate":"28,659.7449","description":"British Pound Sterling","rate_float":28659.7449},"EUR":{"code":"EUR","symbol":"&euro;","rate":"33,358.9812","description":"Euro","rate_float":33358.9812},"CNY":{"code":"CNY","symbol":"&yen;","rate":"40,202.5000","description":"Chinese Yuan","rate_float":40202.5}}}