{"time":{"updated":"Jun 13, 2021 06:17:00 UTC","updatedISO":"2021-06-13T06:17:00+00:00","updateduk":"Jun 13, 2021 at 07:17 BST"},"disclaimer":"This data was produced from the CoinDesk Bitcoin Price Index (USD). Non-USD currency data converted using hourly conversion rate from openexchangerates.org","chartName":"Bitcoin","bpi":{"USD":{"code":"USD","symbol":"&#36;","rate":"35,075.5212","description":"United States Dollar","rate_float":35075.5212},"GBP":{"code":"GBP","symbol":"&pound;","rate":"24,863.0377","description":"British Pound Sterling","rate_float":24863.0377},"EUR":{"code":"EUR","symbol":"&euro;","rate":"28,966.5930","description":"Euro","rate_float":28966.593},"CNY":{"code":"CNY","symbol":"&yen;","rate":"40,202.5000","description":"Chinese Yuan","rate_float":40202.5}}}