{"time":{"updated":"Aug 27, 2021 18:48:00 UTC","updatedISO":"2021-08-27T18:48:00+00:00","updateduk":"Aug 27, 2021 at 19:48 BST"},"disclaimer":"This data was produced from the CoinDesk Bitcoin Price Index (USD). Non-USD currency data converted using hourly conversion rate from openexchangerates.org","chartName":"Bitcoin","bpi":{"USD":{"code":"USD","symbol":"&#36;","rate":"48,387.2708","description":"United States Dollar","rate_float":48387.2708},"GBP":{"code":"GBP","symbol":"&pound;","rate":"35,146.0941","description":"British Pound Sterling","rate_float":35146.0941},"EUR":{"code":"EUR","symbol":"&euro;","rate":"41,023.4540","description":"Euro","rate_float":41023.454},"CNY":{"code":"CNY","symbol":"&yen;","rate":"40,202.5000","description":"Chinese Yuan","rate_float":40202.5}}}