{"time":{"updated":"Sep 7, 2021 11:24:00 UTC","updatedISO":"2021-09-07T11:24:00+00:00","updateduk":"Sep 7, 2021 at 12:24 BST"},"disclaimer":"This data was produced from the CoinDesk Bitcoin Price Index (USD). Non-USD currency data converted using hourly conversion rate from openexchangerates.org","chartName":"Bitcoin","bpi":{"USD":{"code":"USD","symbol":"&#36;","rate":"51,069.4550","description":"United States Dollar","rate_float":51069.455},"GBP":{"code":"GBP","symbol":"&pound;","rate":"37,026.6827","description":"British Pound Sterling","rate_float":37026.6827},"EUR":{"code":"EUR","symbol":"&euro;","rate":"43,007.3244","description":"Euro","rate_float":43007.3244},"CNY":{"code":"CNY","symbol":"&yen;","rate":"40,202.5000","description":"Chinese Yuan","rate_float":40202.5}}}