{"time":{"updated":"Aug 27, 2021 15:53:00 UTC","updatedISO":"2021-08-27T15:53:00+00:00","updateduk":"Aug 27, 2021 at 16:53 BST"},"disclaimer":"This data was produced from the CoinDesk Bitcoin Price Index (USD). Non-USD currency data converted using hourly conversion rate from openexchangerates.org","chartName":"Bitcoin","bpi":{"USD":{"code":"USD","symbol":"&#36;","rate":"48,220.8467","description":"United States Dollar","rate_float":48220.8467},"GBP":{"code":"GBP","symbol":"&pound;","rate":"35,078.3031","description":"British Pound Sterling","rate_float":35078.3031},"EUR":{"code":"EUR","symbol":"&euro;","rate":"40,910.2288","description":"Euro","rate_float":40910.2288},"CNY":{"code":"CNY","symbol":"&yen;","rate":"40,202.5000","description":"Chinese Yuan","rate_float":40202.5}}}