{"time":{"updated":"Aug 28, 2021 13:10:00 UTC","updatedISO":"2021-08-28T13:10:00+00:00","updateduk":"Aug 28, 2021 at 14:10 BST"},"disclaimer":"This data was produced from the CoinDesk Bitcoin Price Index (USD). Non-USD currency data converted using hourly conversion rate from openexchangerates.org","chartName":"Bitcoin","bpi":{"USD":{"code":"USD","symbol":"&#36;","rate":"48,884.7395","description":"United States Dollar","rate_float":48884.7395},"GBP":{"code":"GBP","symbol":"&pound;","rate":"35,513.7856","description":"British Pound Sterling","rate_float":35513.7856},"EUR":{"code":"EUR","symbol":"&euro;","rate":"41,443.8955","description":"Euro","rate_float":41443.8955},"CNY":{"code":"CNY","symbol":"&yen;","rate":"40,202.5000","description":"Chinese Yuan","rate_float":40202.5}}}