{"time":{"updated":"Sep 21, 2021 12:50:00 UTC","updatedISO":"2021-09-21T12:50:00+00:00","updateduk":"Sep 21, 2021 at 13:50 BST"},"disclaimer":"This data was produced from the CoinDesk Bitcoin Price Index (USD). Non-USD currency data converted using hourly conversion rate from openexchangerates.org","chartName":"Bitcoin","bpi":{"USD":{"code":"USD","symbol":"&#36;","rate":"43,357.1550","description":"United States Dollar","rate_float":43357.155},"GBP":{"code":"GBP","symbol":"&pound;","rate":"31,696.1614","description":"British Pound Sterling","rate_float":31696.1614},"EUR":{"code":"EUR","symbol":"&euro;","rate":"36,916.2762","description":"Euro","rate_float":36916.2762},"CNY":{"code":"CNY","symbol":"&yen;","rate":"40,202.5000","description":"Chinese Yuan","rate_float":40202.5}}}