{"time":{"updated":"Aug 4, 2021 14:43:00 UTC","updatedISO":"2021-08-04T14:43:00+00:00","updateduk":"Aug 4, 2021 at 15:43 BST"},"disclaimer":"This data was produced from the CoinDesk Bitcoin Price Index (USD). Non-USD currency data converted using hourly conversion rate from openexchangerates.org","chartName":"Bitcoin","bpi":{"USD":{"code":"USD","symbol":"&#36;","rate":"39,002.1150","description":"United States Dollar","rate_float":39002.115},"GBP":{"code":"GBP","symbol":"&pound;","rate":"27,963.3854","description":"British Pound Sterling","rate_float":27963.3854},"EUR":{"code":"EUR","symbol":"&euro;","rate":"32,801.5588","description":"Euro","rate_float":32801.5588},"CNY":{"code":"CNY","symbol":"&yen;","rate":"40,202.5000","description":"Chinese Yuan","rate_float":40202.5}}}