{"time":{"updated":"May 20, 2021 11:25:00 UTC","updatedISO":"2021-05-20T11:25:00+00:00","updateduk":"May 20, 2021 at 12:25 BST"},"disclaimer":"This data was produced from the CoinDesk Bitcoin Price Index (USD). Non-USD currency data converted using hourly conversion rate from openexchangerates.org","chartName":"Bitcoin","bpi":{"USD":{"code":"USD","symbol":"&#36;","rate":"39,950.1747","description":"United States Dollar","rate_float":39950.1747},"GBP":{"code":"GBP","symbol":"&pound;","rate":"28,276.3341","description":"British Pound Sterling","rate_float":28276.3341},"EUR":{"code":"EUR","symbol":"&euro;","rate":"32,761.2207","description":"Euro","rate_float":32761.2207},"CNY":{"code":"CNY","symbol":"&yen;","rate":"40,202.5000","description":"Chinese Yuan","rate_float":40202.5}}}