{"time":{"updated":"Aug 26, 2021 15:31:00 UTC","updatedISO":"2021-08-26T15:31:00+00:00","updateduk":"Aug 26, 2021 at 16:31 BST"},"disclaimer":"This data was produced from the CoinDesk Bitcoin Price Index (USD). Non-USD currency data converted using hourly conversion rate from openexchangerates.org","chartName":"Bitcoin","bpi":{"USD":{"code":"USD","symbol":"&#36;","rate":"46,925.9373","description":"United States Dollar","rate_float":46925.9373},"GBP":{"code":"GBP","symbol":"&pound;","rate":"34,214.2640","description":"British Pound Sterling","rate_float":34214.264},"EUR":{"code":"EUR","symbol":"&euro;","rate":"39,923.8836","description":"Euro","rate_float":39923.8836},"CNY":{"code":"CNY","symbol":"&yen;","rate":"40,202.5000","description":"Chinese Yuan","rate_float":40202.5}}}