{"time":{"updated":"Aug 1, 2021 23:36:00 UTC","updatedISO":"2021-08-01T23:36:00+00:00","updateduk":"Aug 2, 2021 at 00:36 BST"},"disclaimer":"This data was produced from the CoinDesk Bitcoin Price Index (USD). Non-USD currency data converted using hourly conversion rate from openexchangerates.org","chartName":"Bitcoin","bpi":{"USD":{"code":"USD","symbol":"&#36;","rate":"39,825.6650","description":"United States Dollar","rate_float":39825.665},"GBP":{"code":"GBP","symbol":"&pound;","rate":"28,648.7912","description":"British Pound Sterling","rate_float":28648.7912},"EUR":{"code":"EUR","symbol":"&euro;","rate":"33,556.1495","description":"Euro","rate_float":33556.1495},"CNY":{"code":"CNY","symbol":"&yen;","rate":"40,202.5000","description":"Chinese Yuan","rate_float":40202.5}}}