{"time":{"updated":"Jun 13, 2021 16:14:00 UTC","updatedISO":"2021-06-13T16:14:00+00:00","updateduk":"Jun 13, 2021 at 17:14 BST"},"disclaimer":"This data was produced from the CoinDesk Bitcoin Price Index (USD). Non-USD currency data converted using hourly conversion rate from openexchangerates.org","chartName":"Bitcoin","bpi":{"USD":{"code":"USD","symbol":"&#36;","rate":"36,426.7423","description":"United States Dollar","rate_float":36426.7423},"GBP":{"code":"GBP","symbol":"&pound;","rate":"25,820.8413","description":"British Pound Sterling","rate_float":25820.8413},"EUR":{"code":"EUR","symbol":"&euro;","rate":"30,082.4787","description":"Euro","rate_float":30082.4787},"CNY":{"code":"CNY","symbol":"&yen;","rate":"40,202.5000","description":"Chinese Yuan","rate_float":40202.5}}}