{"time":{"updated":"Aug 19, 2021 23:22:00 UTC","updatedISO":"2021-08-19T23:22:00+00:00","updateduk":"Aug 20, 2021 at 00:22 BST"},"disclaimer":"This data was produced from the CoinDesk Bitcoin Price Index (USD). Non-USD currency data converted using hourly conversion rate from openexchangerates.org","chartName":"Bitcoin","bpi":{"USD":{"code":"USD","symbol":"&#36;","rate":"46,569.3621","description":"United States Dollar","rate_float":46569.3621},"GBP":{"code":"GBP","symbol":"&pound;","rate":"34,155.6467","description":"British Pound Sterling","rate_float":34155.6467},"EUR":{"code":"EUR","symbol":"&euro;","rate":"39,878.1830","description":"Euro","rate_float":39878.183},"CNY":{"code":"CNY","symbol":"&yen;","rate":"40,202.5000","description":"Chinese Yuan","rate_float":40202.5}}}