{"time":{"updated":"Sep 2, 2021 10:59:00 UTC","updatedISO":"2021-09-02T10:59:00+00:00","updateduk":"Sep 2, 2021 at 11:59 BST"},"disclaimer":"This data was produced from the CoinDesk Bitcoin Price Index (USD). Non-USD currency data converted using hourly conversion rate from openexchangerates.org","chartName":"Bitcoin","bpi":{"USD":{"code":"USD","symbol":"&#36;","rate":"50,050.1717","description":"United States Dollar","rate_float":50050.1717},"GBP":{"code":"GBP","symbol":"&pound;","rate":"36,281.7198","description":"British Pound Sterling","rate_float":36281.7198},"EUR":{"code":"EUR","symbol":"&euro;","rate":"42,228.7813","description":"Euro","rate_float":42228.7813},"CNY":{"code":"CNY","symbol":"&yen;","rate":"40,202.5000","description":"Chinese Yuan","rate_float":40202.5}}}