{"time":{"updated":"Sep 5, 2021 18:36:00 UTC","updatedISO":"2021-09-05T18:36:00+00:00","updateduk":"Sep 5, 2021 at 19:36 BST"},"disclaimer":"This data was produced from the CoinDesk Bitcoin Price Index (USD). Non-USD currency data converted using hourly conversion rate from openexchangerates.org","chartName":"Bitcoin","bpi":{"USD":{"code":"USD","symbol":"&#36;","rate":"50,378.1338","description":"United States Dollar","rate_float":50378.1338},"GBP":{"code":"GBP","symbol":"&pound;","rate":"36,334.7756","description":"British Pound Sterling","rate_float":36334.7756},"EUR":{"code":"EUR","symbol":"&euro;","rate":"42,393.3507","description":"Euro","rate_float":42393.3507},"CNY":{"code":"CNY","symbol":"&yen;","rate":"40,202.5000","description":"Chinese Yuan","rate_float":40202.5}}}