{"time":{"updated":"May 22, 2021 13:07:00 UTC","updatedISO":"2021-05-22T13:07:00+00:00","updateduk":"May 22, 2021 at 14:07 BST"},"disclaimer":"This data was produced from the CoinDesk Bitcoin Price Index (USD). Non-USD currency data converted using hourly conversion rate from openexchangerates.org","chartName":"Bitcoin","bpi":{"USD":{"code":"USD","symbol":"&#36;","rate":"38,181.7465","description":"United States Dollar","rate_float":38181.7465},"GBP":{"code":"GBP","symbol":"&pound;","rate":"26,982.6203","description":"British Pound Sterling","rate_float":26982.6203},"EUR":{"code":"EUR","symbol":"&euro;","rate":"31,347.9012","description":"Euro","rate_float":31347.9012},"CNY":{"code":"CNY","symbol":"&yen;","rate":"40,202.5000","description":"Chinese Yuan","rate_float":40202.5}}}