{"time":{"updated":"Jul 7, 2021 22:59:00 UTC","updatedISO":"2021-07-07T22:59:00+00:00","updateduk":"Jul 7, 2021 at 23:59 BST"},"disclaimer":"This data was produced from the CoinDesk Bitcoin Price Index (USD). Non-USD currency data converted using hourly conversion rate from openexchangerates.org","chartName":"Bitcoin","bpi":{"USD":{"code":"USD","symbol":"&#36;","rate":"34,161.5797","description":"United States Dollar","rate_float":34161.5797},"GBP":{"code":"GBP","symbol":"&pound;","rate":"24,752.8315","description":"British Pound Sterling","rate_float":24752.8315},"EUR":{"code":"EUR","symbol":"&euro;","rate":"28,966.0475","description":"Euro","rate_float":28966.0475},"CNY":{"code":"CNY","symbol":"&yen;","rate":"40,202.5000","description":"Chinese Yuan","rate_float":40202.5}}}