{"time":{"updated":"Jun 12, 2021 03:13:00 UTC","updatedISO":"2021-06-12T03:13:00+00:00","updateduk":"Jun 12, 2021 at 04:13 BST"},"disclaimer":"This data was produced from the CoinDesk Bitcoin Price Index (USD). Non-USD currency data converted using hourly conversion rate from openexchangerates.org","chartName":"Bitcoin","bpi":{"USD":{"code":"USD","symbol":"&#36;","rate":"35,740.7967","description":"United States Dollar","rate_float":35740.7967},"GBP":{"code":"GBP","symbol":"&pound;","rate":"25,334.6135","description":"British Pound Sterling","rate_float":25334.6135},"EUR":{"code":"EUR","symbol":"&euro;","rate":"29,516.0008","description":"Euro","rate_float":29516.0008},"CNY":{"code":"CNY","symbol":"&yen;","rate":"40,202.5000","description":"Chinese Yuan","rate_float":40202.5}}}