{"time":{"updated":"Jun 29, 2021 10:33:00 UTC","updatedISO":"2021-06-29T10:33:00+00:00","updateduk":"Jun 29, 2021 at 11:33 BST"},"disclaimer":"This data was produced from the CoinDesk Bitcoin Price Index (USD). Non-USD currency data converted using hourly conversion rate from openexchangerates.org","chartName":"Bitcoin","bpi":{"USD":{"code":"USD","symbol":"&#36;","rate":"35,331.7083","description":"United States Dollar","rate_float":35331.7083},"GBP":{"code":"GBP","symbol":"&pound;","rate":"25,502.9924","description":"British Pound Sterling","rate_float":25502.9924},"EUR":{"code":"EUR","symbol":"&euro;","rate":"29,669.6254","description":"Euro","rate_float":29669.6254},"CNY":{"code":"CNY","symbol":"&yen;","rate":"40,202.5000","description":"Chinese Yuan","rate_float":40202.5}}}