{"time":{"updated":"Sep 1, 2021 19:29:00 UTC","updatedISO":"2021-09-01T19:29:00+00:00","updateduk":"Sep 1, 2021 at 20:29 BST"},"disclaimer":"This data was produced from the CoinDesk Bitcoin Price Index (USD). Non-USD currency data converted using hourly conversion rate from openexchangerates.org","chartName":"Bitcoin","bpi":{"USD":{"code":"USD","symbol":"&#36;","rate":"48,422.1209","description":"United States Dollar","rate_float":48422.1209},"GBP":{"code":"GBP","symbol":"&pound;","rate":"35,141.3373","description":"British Pound Sterling","rate_float":35141.3373},"EUR":{"code":"EUR","symbol":"&euro;","rate":"40,874.6133","description":"Euro","rate_float":40874.6133},"CNY":{"code":"CNY","symbol":"&yen;","rate":"40,202.5000","description":"Chinese Yuan","rate_float":40202.5}}}