{"time":{"updated":"Apr 25, 2021 06:01:00 UTC","updatedISO":"2021-04-25T06:01:00+00:00","updateduk":"Apr 25, 2021 at 07:01 BST"},"disclaimer":"This data was produced from the CoinDesk Bitcoin Price Index (USD). Non-USD currency data converted using hourly conversion rate from openexchangerates.org","chartName":"Bitcoin","bpi":{"USD":{"code":"USD","symbol":"&#36;","rate":"49,844.3250","description":"United States Dollar","rate_float":49844.325},"GBP":{"code":"GBP","symbol":"&pound;","rate":"35,914.5309","description":"British Pound Sterling","rate_float":35914.5309},"EUR":{"code":"EUR","symbol":"&euro;","rate":"41,203.3627","description":"Euro","rate_float":41203.3627},"CNY":{"code":"CNY","symbol":"&yen;","rate":"40,202.5000","description":"Chinese Yuan","rate_float":40202.5}}}