{"time":{"updated":"Jul 26, 2021 00:19:00 UTC","updatedISO":"2021-07-26T00:19:00+00:00","updateduk":"Jul 26, 2021 at 01:19 BST"},"disclaimer":"This data was produced from the CoinDesk Bitcoin Price Index (USD). Non-USD currency data converted using hourly conversion rate from openexchangerates.org","chartName":"Bitcoin","bpi":{"USD":{"code":"USD","symbol":"&#36;","rate":"35,722.3567","description":"United States Dollar","rate_float":35722.3567},"GBP":{"code":"GBP","symbol":"&pound;","rate":"25,966.4382","description":"British Pound Sterling","rate_float":25966.4382},"EUR":{"code":"EUR","symbol":"&euro;","rate":"30,342.6412","description":"Euro","rate_float":30342.6412},"CNY":{"code":"CNY","symbol":"&yen;","rate":"40,202.5000","description":"Chinese Yuan","rate_float":40202.5}}}