{"time":{"updated":"Sep 7, 2021 07:55:00 UTC","updatedISO":"2021-09-07T07:55:00+00:00","updateduk":"Sep 7, 2021 at 08:55 BST"},"disclaimer":"This data was produced from the CoinDesk Bitcoin Price Index (USD). Non-USD currency data converted using hourly conversion rate from openexchangerates.org","chartName":"Bitcoin","bpi":{"USD":{"code":"USD","symbol":"&#36;","rate":"52,462.5830","description":"United States Dollar","rate_float":52462.583},"GBP":{"code":"GBP","symbol":"&pound;","rate":"37,930.5000","description":"British Pound Sterling","rate_float":37930.5},"EUR":{"code":"EUR","symbol":"&euro;","rate":"44,193.5356","description":"Euro","rate_float":44193.5356},"CNY":{"code":"CNY","symbol":"&yen;","rate":"40,202.5000","description":"Chinese Yuan","rate_float":40202.5}}}