{"time":{"updated":"May 13, 2021 19:28:00 UTC","updatedISO":"2021-05-13T19:28:00+00:00","updateduk":"May 13, 2021 at 20:28 BST"},"disclaimer":"This data was produced from the CoinDesk Bitcoin Price Index (USD). Non-USD currency data converted using hourly conversion rate from openexchangerates.org","chartName":"Bitcoin","bpi":{"USD":{"code":"USD","symbol":"&#36;","rate":"48,892.2250","description":"United States Dollar","rate_float":48892.225},"GBP":{"code":"GBP","symbol":"&pound;","rate":"34,818.2069","description":"British Pound Sterling","rate_float":34818.2069},"EUR":{"code":"EUR","symbol":"&euro;","rate":"40,486.6737","description":"Euro","rate_float":40486.6737},"CNY":{"code":"CNY","symbol":"&yen;","rate":"40,202.5000","description":"Chinese Yuan","rate_float":40202.5}}}