{"time":{"updated":"Sep 26, 2021 17:19:00 UTC","updatedISO":"2021-09-26T17:19:00+00:00","updateduk":"Sep 26, 2021 at 18:19 BST"},"disclaimer":"This data was produced from the CoinDesk Bitcoin Price Index (USD). Non-USD currency data converted using hourly conversion rate from openexchangerates.org","chartName":"Bitcoin","bpi":{"USD":{"code":"USD","symbol":"&#36;","rate":"43,294.6567","description":"United States Dollar","rate_float":43294.6567},"GBP":{"code":"GBP","symbol":"&pound;","rate":"31,636.5746","description":"British Pound Sterling","rate_float":31636.5746},"EUR":{"code":"EUR","symbol":"&euro;","rate":"36,940.5164","description":"Euro","rate_float":36940.5164},"CNY":{"code":"CNY","symbol":"&yen;","rate":"40,202.5000","description":"Chinese Yuan","rate_float":40202.5}}}