{"time":{"updated":"Jul 14, 2021 23:31:00 UTC","updatedISO":"2021-07-14T23:31:00+00:00","updateduk":"Jul 15, 2021 at 00:31 BST"},"disclaimer":"This data was produced from the CoinDesk Bitcoin Price Index (USD). Non-USD currency data converted using hourly conversion rate from openexchangerates.org","chartName":"Bitcoin","bpi":{"USD":{"code":"USD","symbol":"&#36;","rate":"32,771.9683","description":"United States Dollar","rate_float":32771.9683},"GBP":{"code":"GBP","symbol":"&pound;","rate":"23,647.2364","description":"British Pound Sterling","rate_float":23647.2364},"EUR":{"code":"EUR","symbol":"&euro;","rate":"27,688.3478","description":"Euro","rate_float":27688.3478},"CNY":{"code":"CNY","symbol":"&yen;","rate":"40,202.5000","description":"Chinese Yuan","rate_float":40202.5}}}