{"time":{"updated":"Jul 2, 2021 04:46:00 UTC","updatedISO":"2021-07-02T04:46:00+00:00","updateduk":"Jul 2, 2021 at 05:46 BST"},"disclaimer":"This data was produced from the CoinDesk Bitcoin Price Index (USD). Non-USD currency data converted using hourly conversion rate from openexchangerates.org","chartName":"Bitcoin","bpi":{"USD":{"code":"USD","symbol":"&#36;","rate":"33,042.8026","description":"United States Dollar","rate_float":33042.8026},"GBP":{"code":"GBP","symbol":"&pound;","rate":"23,999.6154","description":"British Pound Sterling","rate_float":23999.6154},"EUR":{"code":"EUR","symbol":"&euro;","rate":"27,900.5495","description":"Euro","rate_float":27900.5495},"CNY":{"code":"CNY","symbol":"&yen;","rate":"40,202.5000","description":"Chinese Yuan","rate_float":40202.5}}}