{"time":{"updated":"Jul 27, 2021 23:39:00 UTC","updatedISO":"2021-07-27T23:39:00+00:00","updateduk":"Jul 28, 2021 at 00:39 BST"},"disclaimer":"This data was produced from the CoinDesk Bitcoin Price Index (USD). Non-USD currency data converted using hourly conversion rate from openexchangerates.org","chartName":"Bitcoin","bpi":{"USD":{"code":"USD","symbol":"&#36;","rate":"38,961.2650","description":"United States Dollar","rate_float":38961.265},"GBP":{"code":"GBP","symbol":"&pound;","rate":"28,071.1239","description":"British Pound Sterling","rate_float":28071.1239},"EUR":{"code":"EUR","symbol":"&euro;","rate":"32,971.5160","description":"Euro","rate_float":32971.516},"CNY":{"code":"CNY","symbol":"&yen;","rate":"40,202.5000","description":"Chinese Yuan","rate_float":40202.5}}}