{"time":{"updated":"Jul 2, 2021 08:13:00 UTC","updatedISO":"2021-07-02T08:13:00+00:00","updateduk":"Jul 2, 2021 at 09:13 BST"},"disclaimer":"This data was produced from the CoinDesk Bitcoin Price Index (USD). Non-USD currency data converted using hourly conversion rate from openexchangerates.org","chartName":"Bitcoin","bpi":{"USD":{"code":"USD","symbol":"&#36;","rate":"33,467.6611","description":"United States Dollar","rate_float":33467.6611},"GBP":{"code":"GBP","symbol":"&pound;","rate":"24,322.2211","description":"British Pound Sterling","rate_float":24322.2211},"EUR":{"code":"EUR","symbol":"&euro;","rate":"28,302.6304","description":"Euro","rate_float":28302.6304},"CNY":{"code":"CNY","symbol":"&yen;","rate":"40,202.5000","description":"Chinese Yuan","rate_float":40202.5}}}